.DS_Store
autodh/__init__.py
autodh/autodh.py
autodh/dh_table.py
autodh/joint.py
autodh/math_utils.py
AutoDH-0.2.dist-info/LICENSE
AutoDH-0.2.dist-info/METADATA
AutoDH-0.2.dist-info/WHEEL
AutoDH-0.2.dist-info/top_level.txt
AutoDH-0.2.dist-info/RECORD
