Metadata-Version: 2.1
Name: AutoDH
Version: 0.2
Summary: Library for automatic extraction of Denavit-Hartenberg parameters
Home-page: https://github.com/edsterg/autodh
Author: Eddie Groshev
License: MIT
Keywords: autdh automatic dh denavit-hartenberg robotics robot
Platform: UNKNOWN
Classifier: License :: OSI Approved :: MIT License
Classifier: Programming Language :: Python :: 2.7
Classifier: Programming Language :: Python :: 3
Provides-Extra: test
